{
    "New York City": {
        "schedule": {
            "3f660e58-fa44-4de6-bbe5-2ff5d47c14a0": [
                "2020-12-05T14:00",
                "2020-12-05T15:00"
            ],
            "949c2021-4bda-4fb3-92ab-0a5bf7e167e5": [
                "2021-06-01T10:00",
                "2021-06-01T11:30"
            ]
        },
        "capacity": 15
    },
    "Asgard": {
        "schedule": {"c463b726-f5ca-4dd5-b772-7801a421c111": [
            "2021-06-10T13:00",
            "2021-06-10T15:15"
        ]},
        "capacity": 4
    },
    "Avengers Mansion": {
        "schedule": {
            "4eab691f-0d69-4e63-9ffa-4138f5c5ed5e": [
                "2020-12-01T10:00",
                "2020-12-01T12:00"
            ],
            "937b16e8-6cb4-419a-a547-ab1b13bd8d9d": [
                "2021-06-06T12:00",
                "2021-06-06T13:00"
            ],
            "3b145c56-65da-4ed2-9b53-471687e26b16": [
                "2021-06-06T09:00",
                "2021-06-06T10:30"
            ],
            "0d9a58c0-0503-4073-b6d5-238d357987da": [
                "2021-06-05T14:00",
                "2021-06-05T15:00"
            ]
        },
        "capacity": 11
    },
    "Stark Tower": {
        "schedule": {
            "418b8a42-4844-49ba-8b0b-d200761e635e": [
                "2021-06-07T10:00",
                "2021-06-07T15:30"
            ],
            "0d5912ed-db0c-4373-bf02-71236c720a68": [
                "2021-06-05T13:00",
                "2021-06-05T16:00"
            ]
        },
        "capacity": 11
    },
    "Wakanda": {
        "schedule": {
            "bc5daa43-1a98-4c86-a38c-72548794deab": [
                "2021-06-07T11:00",
                "2021-06-07T12:45"
            ],
            "99b5e204-d17c-43cf-ab5f-b5226182760a": [
                "2021-06-07T09:30",
                "2021-06-07T11:00"
            ]
        },
        "capacity": 7
    }
}